{
	"info": {
		"_postman_id": "d2a79bc3-df7a-4714-a308-afeafb86bba3",
		"name": "University",
		"schema": "https://schema.getpostman.com/json/collection/v2.1.0/collection.json",
		"_exporter_id": "21718862"
	},
	"item": [
		{
			"name": "GET ID",
			"request": {
				"method": "GET",
				"header": []
			},
			"response": []
		},
		{
			"name": "GET ALL",
			"request": {
				"method": "GET",
				"header": []
			},
			"response": []
		},
		{
			"name": "UPDATE",
			"request": {
				"method": "PUT",
				"header": [],
				"body": {
					"mode": "raw",
					"raw": "{\r\n    \"id\":2,\r\n    \"name\":\"Svayz\",\r\n    \"address\":\"selhoz\",\r\n    \"openYear\":\"2002-02-12\"\r\n   \r\n}",
					"options": {
						"raw": {
							"language": "json"
						}
					}
				},
				"url": {
					"raw": "localhost:8080/university/update",
					"host": [
						"localhost"
					],
					"port": "8080",
					"path": [
						"university",
						"update"
					]
				}
			},
			"response": []
		},
		{
			"name": "DELETE",
			"request": {
				"method": "GET",
				"header": []
			},
			"response": []
		},
		{
			"name": "ADD",
			"request": {
				"method": "GET",
				"header": []
			},
			"response": []
		}
	]
}